pygdg/__init__.py
pygdg/common.py
pygdg/events.py
pygdg/features.py
pygdg/main.py
pygdg/options.py
pygdg-0.1.6.dist-info/LICENSE
pygdg-0.1.6.dist-info/METADATA
pygdg-0.1.6.dist-info/WHEEL
pygdg-0.1.6.dist-info/entry_points.txt
pygdg-0.1.6.dist-info/top_level.txt
pygdg-0.1.6.dist-info/RECORD
