Metadata-Version: 2.1
Name: pygdg
Version: 0.1.6
Summary: A simple comand line tool to create game events data for analytics and machine learning use cases
Home-page: https://github.com/growak/pygdg
Author: GroWaK
Author-email: me@growak.org
Project-URL: Project Tracker, https://github.com/growak/pygdg/projects
Project-URL: Issue Tracker, https://github.com/growak/pygdg/issues
Keywords: game machine learning analytics dataset generator
Classifier: Programming Language :: Python :: 3
Classifier: License :: OSI Approved :: MIT License
Classifier: Operating System :: OS Independent
Requires-Python: >=3.6
License-File: LICENSE
Requires-Dist: click
Requires-Dist: numpy
Requires-Dist: pandas
Requires-Dist: matplotlib
